myProject/__init__.py
myProject/hw4.py
Husna_Ocmaz_final_project-0.0.2.dist-info/LICENSE
Husna_Ocmaz_final_project-0.0.2.dist-info/METADATA
Husna_Ocmaz_final_project-0.0.2.dist-info/WHEEL
Husna_Ocmaz_final_project-0.0.2.dist-info/top_level.txt
Husna_Ocmaz_final_project-0.0.2.dist-info/RECORD
