Metadata-Version: 2.1
Name: Husna_Ocmaz_final_project
Version: 0.0.2
Summary: Assignment 4 package
Author-email: Husna Ocmaz <husna.ocmaz@bahcesehir.edu.tr>
Project-URL: Homepage, https://github.com/HELONA6/final-project
Classifier: Programming Language :: Python :: 3
Classifier: License :: OSI Approved :: MIT License
Classifier: Operating System :: OS Independent
Requires-Python: >=3.5
License-File: LICENSE
